setup.py
cstar_perf/__init__.py
cstar_perf.tool.egg-info/PKG-INFO
cstar_perf.tool.egg-info/SOURCES.txt
cstar_perf.tool.egg-info/dependency_links.txt
cstar_perf.tool.egg-info/entry_points.txt
cstar_perf.tool.egg-info/namespace_packages.txt
cstar_perf.tool.egg-info/not-zip-safe
cstar_perf.tool.egg-info/requires.txt
cstar_perf.tool.egg-info/top_level.txt
cstar_perf/tool/__init__.py
cstar_perf/tool/benchmark.py
cstar_perf/tool/bootstrap.py
cstar_perf/tool/cluster_config.py
cstar_perf/tool/fab_cassandra.py
cstar_perf/tool/fincore_capture.py
cstar_perf/tool/stress_compare.py
cstar_perf/tool/util.py