Metadata-Version: 1.1
Name: cstar-perf.tool
Version: 1.0
Summary: Cassandra performance testing automation tools
Home-page: https://github.com/datastax/cstar_perf
Author: The DataStax Cassandra Test Engineering Team
Author-email: ryan@datastax.com
License: UNKNOWN
Platform: UNKNOWN
Classifier: Programming Language :: Python :: 2.7
Classifier: Programming Language :: Python :: Implementation :: CPython
Classifier: Topic :: Software Development :: Libraries :: Python Modules
